py3nt/__init__.py
py3nt/congruence/__init__.py
py3nt/congruence/basics.py
py3nt/congruence/binomial.py
py3nt/congruence/primitives.py
py3nt/congruence/quadratic.py
py3nt/core/__init__.py
py3nt/core/base.py
py3nt/core/factorize.py
py3nt/core/primality_test.py
py3nt/core/sieve.py
py3nt/defaults.py
py3nt/functions/__init__.py
py3nt/functions/binary/__init__.py
py3nt/functions/unary/__init__.py
py3nt/functions/unary/divisor_functions.py
py3nt/functions/unary/totient.py
py3nt/numbers/__init__.py
py3nt/numbers/integer.py
py3nt/polynomial/__init__.py
py3nt/polynomial/binomial.py
py3nt-2.1.24.dist-info/LICENSE
py3nt-2.1.24.dist-info/METADATA
py3nt-2.1.24.dist-info/WHEEL
py3nt-2.1.24.dist-info/RECORD
