Metadata-Version: 2.1
Name: py3nt
Version: 2.1.24
Summary: A Number Theory Library for Python 3
Home-page: https://github.com/math-projects/pynt
License: MIT
Author: Masum Billal
Author-email: billalmasum93@gmail.com
Requires-Python: >=3.9,<4.0
Classifier: License :: OSI Approved :: MIT License
Classifier: Programming Language :: Python :: 3
Classifier: Programming Language :: Python :: 3.9
Classifier: Programming Language :: Python :: 3.10
Classifier: Programming Language :: Python :: 3.11
Requires-Dist: numpy (>=1.24.2)
Requires-Dist: sympy (>=1.11)
Project-URL: Repository, https://github.com/math-projects/pynt
